apispec_helper/__init__.py
apispec_helper/_internal_utils/__init__.py
apispec_helper/_internal_utils/dataclass_helper_base.py
apispec_helper/_internal_utils/mutual_exclusive_field_checker.py
apispec_helper/_internal_utils/one_of_field_checker.py
apispec_helper/_internal_utils/post_init_base.py
apispec_helper/basic_type/__init__.py
apispec_helper/basic_type/common_type.py
apispec_helper/basic_type/examples.py
apispec_helper/basic_type/external_documentation.py
apispec_helper/basic_type/server.py
apispec_helper/component/__init__.py
apispec_helper/component/component_base.py
apispec_helper/component/content.py
apispec_helper/component/header.py
apispec_helper/component/link.py
apispec_helper/component/parameter.py
apispec_helper/component/parameter_style.py
apispec_helper/component/request_body.py
apispec_helper/component/response.py
apispec_helper/component/security_scheme.py
apispec_helper/path/__init__.py
apispec_helper/path/path_base.py
apispec_helper/path/path_item.py
apispec_helper/utils/__init__.py
apispec_helper/utils/to_dict.py
apispec_helper-0.2.4.dist-info/LICENSE
apispec_helper-0.2.4.dist-info/METADATA
apispec_helper-0.2.4.dist-info/WHEEL
apispec_helper-0.2.4.dist-info/RECORD
