Metadata-Version: 2.1
Name: apispec-helper
Version: 0.2.4
Summary: This project provides objective oriented helper classes collection for defining OpenAPI objects in [apispec](https://pypi.org/project/apispec/).
Home-page: https://github.com/HallBlazzar/apispec-helper
License: MIT
Keywords: openapi,apispec
Author: hallblazzar
Author-email: hallblazzar@gmail.com
Requires-Python: >=3.7,<4.0
Classifier: Development Status :: 2 - Pre-Alpha
Classifier: License :: OSI Approved :: MIT License
Classifier: Programming Language :: Python :: 3
Classifier: Programming Language :: Python :: 3.7
Classifier: Programming Language :: Python :: 3.8
Classifier: Programming Language :: Python :: 3.9
Classifier: Programming Language :: Python :: 3.10
Classifier: Programming Language :: Python :: 3.11
Classifier: Topic :: Software Development :: Documentation
Project-URL: Repository, https://github.com/HallBlazzar/apispec-helper
